{
  "ModelName": "SK-105 \"Kürassier\"",
  "ManufacturerId": null,
  "PriceId": null,
  "ManufacturerReference": {
    "Id": 0,
    "Name": "Steyr",
    "CountryName": "Austria",
    "BudgetId": null,
    "BudgetReference": null
  },
  "PriceReference": null,
  "Id": 0,
  "CrewCount": 4,
  "GunId": null,
  "EngineId": null,
  "GunReference": {
    "ModelName": "CN 105 G1",
    "ManufacturerId": null,
    "PriceId": null,
    "ManufacturerReference": {
      "Id": 0,
      "Name": "arsenal de Bourges (ABS)",
      "CountryName": "France",
      "BudgetId": null,
      "BudgetReference": null
    },
    "PriceReference": null,
    "Id": null,
    "CaliberMillimetres": 105,
    "LengthInCalibers": 44.019047619
  },
  "EngineReference": {
    "ModelName": "Steyr 7FA",
    "ManufacturerId": null,
    "PriceId": null,
    "ManufacturerReference": {
      "Id": 0,
      "Name": "Steyr",
      "CountryName": "Austria",
      "BudgetId": null,
      "BudgetReference": null
    },
    "PriceReference": null,
    "Id": 0,
    "HorsePowers": 320
  }
}