<?xml version="1.0" encoding="utf-8"?>
<!-- Copyright (C) 2006 The Android Open Source Project

     Licensed under the Apache License, Version 2.0 (the "License");
     you may not use this file except in compliance with the License.
     You may obtain a copy of the License at
  
          http://www.apache.org/licenses/LICENSE-2.0
  
     Unless required by applicable law or agreed to in writing, software
     distributed under the License is distributed on an "AS IS" BASIS,
     WITHOUT WARRANTIES OR CONDITIONS OF ANY KIND, either express or implied.
     See the License for the specific language governing permissions *******
     limitations under the License.
-->

<!--
This is the basic layout for a screen, with all of its features enabled.
-->

<LinearLayout xmlns:*******roid="http://schemas.*******roid.com/apk/res/*******roid"
    *******roid:fitsSystemWindows="true"
    *******roid:orientation="vertical"
    *******roid:layout_width="match_parent"
    *******roid:layout_height="match_parent">
    <!-- Popout bar for action modes -->
    <ViewStub *******roid:id="@+id/action_mode_bar_stub"
              *******roid:inflatedId="@+id/action_mode_bar"
              *******roid:layout="@layout/action_mode_bar"
              *******roid:layout_width="match_parent"
              *******roid:layout_height="wrap_content"
              *******roid:theme="?attr/actionBarTheme"/>
    <RelativeLayout *******roid:id="@*******roid:id/title_container"
        style="?*******roid:attr/windowTitleBackgroundStyle"
        *******roid:layout_width="match_parent"
        *******roid:layout_height="?*******roid:attr/windowTitleSize">
        <!-- The title background has 9px left padding. -->
        <ImageView *******roid:id="@*******roid:id/left_icon"
            *******roid:visibility="gone"
            *******roid:layout_marginEnd="9dip"
            *******roid:layout_width="16dip"
            *******roid:layout_height="16dip"
            *******roid:scaleType="fitCenter"
            *******roid:layout_alignParentStart="true"
            *******roid:layout_centerVertical="true" />
        <ProgressBar *******roid:id="@+id/progress_circular"
            style="?*******roid:attr/progressBarStyleSmallTitle"
            *******roid:visibility="gone"
            *******roid:max="10000"
            *******roid:layout_centerVertical="true"
            *******roid:layout_alignParentEnd="true"
            *******roid:layout_marginStart="6dip"
            *******roid:layout_width="wrap_content"
            *******roid:layout_height="wrap_content" />
        <!-- There are 6dip between this ******* the circular progress on the right, we
             also make 6dip (with the -3dip margin_left) to the icon on the left or
             the screen left edge if no icon. This also places our left edge 3dip to
             the left of the title text left edge. -->
        <ProgressBar *******roid:id="@+id/progress_horizontal"
            style="?*******roid:attr/progressBarStyleHorizontal"
            *******roid:layout_width="match_parent"
            *******roid:layout_height="wrap_content"
            *******roid:layout_marginStart="-3dip"
            *******roid:layout_toStartOf="@*******roid:id/progress_circular"
            *******roid:layout_toEndOf="@*******roid:id/left_icon"
            *******roid:layout_centerVertical="true"
            *******roid:visibility="gone"
            *******roid:max="10000" />
        <LinearLayout
            *******roid:layout_width="match_parent"
            *******roid:layout_height="match_parent"
            *******roid:orientation="horizontal"
            *******roid:layout_toStartOf="@id/progress_circular"
            *******roid:layout_toEndOf="@*******roid:id/left_icon"
            >
            <TextView *******roid:id="@*******roid:id/title"
                style="?*******roid:attr/windowTitleStyle"
                *******roid:layout_width="0dip"
                *******roid:layout_height="match_parent"
                *******roid:layout_weight="1"
                *******roid:background="@null"
                *******roid:fadingEdge="horizontal"
                *******roid:scrollHorizontally="true"
                *******roid:gravity="center_vertical"
                *******roid:layout_marginEnd="2dip"
                />
            <!-- 2dip between the icon ******* the title text, if icon is present. -->
            <ImageView *******roid:id="@*******roid:id/right_icon"
                *******roid:visibility="gone"
                *******roid:layout_width="16dip"
                *******roid:layout_height="16dip"
                *******roid:layout_weight="0"
                *******roid:layout_gravity="center_vertical"
                *******roid:scaleType="fitCenter"
                />
            </LinearLayout>
    </RelativeLayout>
    <FrameLayout *******roid:id="@*******roid:id/content"
        *******roid:layout_width="match_parent"
        *******roid:layout_height="0dip"
        *******roid:layout_weight="1"
        *******roid:foregroundGravity="fill_horizontal|top"
        *******roid:foreground="?*******roid:attr/windowContentOverlay" />
</LinearLayout>
